midi_to_dataframe/__init__.py
midi_to_dataframe/midi_reader.py
midi_to_dataframe/midi_writer.py
midi_to_dataframe/note_mapper.py
midi_to_dataframe/midi/__init__.py
midi_to_dataframe/midi/constants.py
midi_to_dataframe/midi/containers.py
midi_to_dataframe/midi/events.py
midi_to_dataframe/midi/fileio.py
midi_to_dataframe/midi/sequencer.py
midi_to_dataframe/midi/util.py
tests/__init__.py
tests/tests.py
midi_to_dataframe-0.4.3.dist-info/LICENSE
midi_to_dataframe-0.4.3.dist-info/METADATA
midi_to_dataframe-0.4.3.dist-info/WHEEL
midi_to_dataframe-0.4.3.dist-info/top_level.txt
midi_to_dataframe-0.4.3.dist-info/RECORD
