Metadata-Version: 2.2
Name: midi_to_dataframe
Version: 0.4.3
Summary: Python library for converting between MIDI files and Pandas DataFrame objects.
Home-page: https://github.com/TaylorPeer/midi-to-dataframe
Author: Taylor Peer
License: Apache License 2.0
License-File: LICENSE
Requires-Dist: pandas<3.0.0
Dynamic: author
Dynamic: description
Dynamic: description-content-type
Dynamic: home-page
Dynamic: license
Dynamic: requires-dist
Dynamic: summary
